ict_vscl/DigitalHuman.py
ict_vscl/Public.py
ict_vscl/Robot.py
ict_vscl/UAV.py
ict_vscl/__init__.py
ict_vscl/core.py
ict_vscl-1.0.dist-info/METADATA
ict_vscl-1.0.dist-info/WHEEL
ict_vscl-1.0.dist-info/top_level.txt
ict_vscl-1.0.dist-info/RECORD
