Metadata-Version: 2.1
Name: ict-vscl
Version: 1.0
Summary: 深职院智能ict三维编程拓展组件
Home-page: UNKNOWN
Author: UNKNOWN
Author-email: UNKNOWN
License: UNKNOWN
Platform: UNKNOWN
Requires-Dist: websocket-client (==1.5.2)
